grpc_api_client/__init__.py
grpc_api_client/client.py
grpc_api_client/client_test.py
grpc_api_client/grpc/__init__.py
grpc_api_client/grpc/api.py
grpc_api_client/grpc/api_test.py
grpc_api_client/grpc/bindings.py
grpc_api_client/grpc/channel.py
grpc_api_client/grpc/channel_test.py
grpc_api_client/grpc/interface.py
grpc_api_client/grpc/interface_test.py
grpc_api_client/grpc/settings.py
grpc_api_client/grpc/sample/__init__.py
grpc_api_client/grpc/sample/api_pb2.py
grpc_api_client/grpc/sample/api_pb2_grpc.py
grpc_api_client/grpc/sample/api_pb2_server.py
grpc_api_client-0.1.1.dist-info/LICENSE
grpc_api_client-0.1.1.dist-info/METADATA
grpc_api_client-0.1.1.dist-info/WHEEL
grpc_api_client-0.1.1.dist-info/top_level.txt
grpc_api_client-0.1.1.dist-info/RECORD
